{
"Procedures":[
	{
    "Columns": [
        {
            "Name": "database_id",
            "DataType": 1,
            "Values": [
                ""
            ]
        },
        {
            "Name": "backup_set_id",
            "DataType": 1,
            "Values": [
                ""
            ]
        },
        {
            "Name": "backup_set_uuid",
            "DataType": 1,
            "Values": [
                ""
            ]
        },
        {
            "Name": "first_family_number",
            "DataType": 1,
            "Values": [
                ""
            ]
        },
        {
            "Name": "first_media_number",
            "DataType": 1,
            "Values": [
                ""
            ]
        },
        {
            "Name": "last_family_number",
            "DataType": 1,
            "Values": [
                ""
            ]
        },
        {
            "Name": "last_media_number",
            "DataType": 1,
            "Values": [
                ""
            ]
        },
        {
            "Name": "catalog_family_number",
            "DataType": 1,
            "Values": [
                ""
            ]
        },
        {
            "Name": "catalog_media_number",
            "DataType": 1,
            "Values": [
                ""
            ]
        },
        {
            "Name": "position",
            "DataType": 1,
            "Values": [
                ""
            ]
        },
        {
            "Name": "expiration_date",
            "DataType": 1,
            "Values": [
                ""
            ]
        },
        {
            "Name": "software_vendor_id",
            "DataType": 1,
            "Values": [
                ""
            ]
        },
        {
            "Name": "name",
            "DataType": 1,
            "Values": [
                ""
            ]
        },
        {
            "Name": "description",
            "DataType": 1,
            "Values": [
                ""
            ]
        },
        {
            "Name": "user_name",
            "DataType": 1,
            "Values": [
                ""
            ]
        },
        {
            "Name": "software_major_version",
            "DataType": 1,
            "Values": [
                ""
            ]
        },
        {
            "Name": "software_minor_version",
            "DataType": 1,
            "Values": [
                ""
            ]
        },
        {
            "Name": "software_build_version",
            "DataType": 1,
            "Values": [
                ""
            ]
        },
        {
            "Name": "time_zone",
            "DataType": 1,
            "Values": [
                ""
            ]
        },
        {
            "Name": "mtf_minor_version",
            "DataType": 1,
            "Values": [
                ""
            ]
        },
        {
            "Name": "first_lsn",
            "DataType": 1,
            "Values": [
                ""
            ]
        },
        {
            "Name": "last_lsn",
            "DataType": 1,
            "Values": [
                ""
            ]
        },
        {
            "Name": "checkpoint_lsn",
            "DataType": 1,
            "Values": [
                ""
            ]
        },
        {
            "Name": "database_backup_lsn",
            "DataType": 1,
            "Values": [
                ""
            ]
        },
        {
            "Name": "database_creation_date",
            "DataType": 1,
            "Values": [
                ""
            ]
        },
        {
            "Name": "backup_start_date",
            "DataType": 1,
            "Values": [
                ""
            ]
        },
        {
            "Name": "backup_finish_date",
            "DataType": 1,
            "Values": [
                ""
            ]
        },
        {
            "Name": "type",
            "DataType": 1,
            "Values": [
                ""
            ]
        },
        {
            "Name": "sort_order",
            "DataType": 1,
            "Values": [
                ""
            ]
        },
        {
            "Name": "code_page",
            "DataType": 1,
            "Values": [
                ""
            ]
        },
        {
            "Name": "compatibility_level",
            "DataType": 1,
            "Values": [
                ""
            ]
        },
        {
            "Name": "database_version",
            "DataType": 1,
            "Values": [
                ""
            ]
        },
        {
            "Name": "backup_size",
            "DataType": 1,
            "Values": [
                ""
            ]
        },
        {
            "Name": "database_name",
            "DataType": 1,
            "Values": [
                ""
            ]
        },
        {
            "Name": "server_name",
            "DataType": 1,
            "Values": [
                ""
            ]
        },
        {
            "Name": "machine_name",
            "DataType": 1,
            "Values": [
                ""
            ]
        },
        {
            "Name": "flags",
            "DataType": 1,
            "Values": [
                ""
            ]
        },
        {
            "Name": "unicode_locale",
            "DataType": 1,
            "Values": [
                ""
            ]
        },
        {
            "Name": "unicode_compare_style",
            "DataType": 1,
            "Values": [
                ""
            ]
        },
        {
            "Name": "collation_name",
            "DataType": 1,
            "Values": [
                ""
            ]
        },
        {
            "Name": "is_password_protected",
            "DataType": 1,
            "Values": [
                ""
            ]
        },
        {
            "Name": "recovery_model",
            "DataType": 1,
            "Values": [
                ""
            ]
        },
        {
            "Name": "has_bulk_logged_data",
            "DataType": 1,
            "Values": [
                ""
            ]
        },
        {
            "Name": "is_snapshot",
            "DataType": 1,
            "Values": [
                ""
            ]
        },
        {
            "Name": "is_readonly",
            "DataType": 1,
            "Values": [
                ""
            ]
        },
        {
            "Name": "is_single_user",
            "DataType": 1,
            "Values": [
                ""
            ]
        },
        {
            "Name": "has_backup_checksums",
            "DataType": 1,
            "Values": [
                ""
            ]
        },
        {
            "Name": "is_damaged",
            "DataType": 1,
            "Values": [
                ""
            ]
        },
        {
            "Name": "begins_log_chain",
            "DataType": 1,
            "Values": [
                ""
            ]
        },
        {
            "Name": "has_incomplete_metadata",
            "DataType": 1,
            "Values": [
                ""
            ]
        },
        {
            "Name": "is_force_offline",
            "DataType": 1,
            "Values": [
                ""
            ]
        },
        {
            "Name": "is_copy_only",
            "DataType": 1,
            "Values": [
                ""
            ]
        },
        {
            "Name": "first_recovery_fork_guid",
            "DataType": 1,
            "Values": [
                ""
            ]
        },
        {
            "Name": "last_recovery_fork_guid",
            "DataType": 1,
            "Values": [
                ""
            ]
        },
        {
            "Name": "fork_point_lsn",
            "DataType": 1,
            "Values": [
                ""
            ]
        },
        {
            "Name": "database_guid",
            "DataType": 1,
            "Values": [
                ""
            ]
        },
        {
            "Name": "family_guid",
            "DataType": 1,
            "Values": [
                ""
            ]
        },
        {
            "Name": "differential_base_lsn",
            "DataType": 1,
            "Values": [
                ""
            ]
        },
        {
            "Name": "differential_base_guid",
            "DataType": 1,
            "Values": [
                ""
            ]
        },
        {
            "Name": "compressed_backup_size",
            "DataType": 1,
            "Values": [
                ""
            ]
        },
        {
            "Name": "media_set_id",
            "DataType": 1,
            "Values": [
                ""
            ]
        },
        {
            "Name": "family_sequence_number",
            "DataType": 1,
            "Values": [
                ""
            ]
        },
        {
            "Name": "media_family_id",
            "DataType": 1,
            "Values": [
                ""
            ]
        },
        {
            "Name": "media_count",
            "DataType": 1,
            "Values": [
                ""
            ]
        },
        {
            "Name": "logical_device_name",
            "DataType": 1,
            "Values": [
                ""
            ]
        },
        {
            "Name": "physical_device_name",
            "DataType": 1,
            "Values": [
                ""
            ]
        },
        {
            "Name": "device_type",
            "DataType": 1,
            "Values": [
                ""
            ]
        },
        {
            "Name": "physical_block_size",
            "DataType": 1,
            "Values": [
                ""
            ]
        },
        {
            "Name": "mirror",
            "DataType": 1,
            "Values": [
                ""
            ]
        },
        {
            "Name": "rownum",
            "DataType": 1,
            "Values": [
                ""
            ]
        },
        {
            "Name": "instance",
            "DataType": 1,
            "Values": [
                "ZHUW2K8R2SPL300\\SQL2008R2"
            ]
        },
        {
            "Name": "service",
            "DataType": 1,
            "Values": [
                "SQL2008R2"
            ]
        },
        {
            "Name": "instance_start_time_utc",
            "DataType": 5,
            "Values": [
                "2016-06-16T03:35:50.083-07:00"
            ]
        }
    ],
	"Timestamp": "{{Timestamp}}",
    "ConnectionName": "zhuw2k8r2spl300.melquest.dev.mel.au.qsft_sql2008r2_sqlserver",
    "PackageName": "sqlserver_spotlight",
    "ProcedureName": "healthcheckdatabasebackups",
    "TechnologyName": "database/sqlserver",
    "DiagnosticServerHost": "DSGDQJDS71:3843",
    "DiagnosticServerID": "54ab6b58-8931-46dd-88ae-b9e80c7195c0",
    "OwnerID": 29939,
    "OwnerGuid": "e475bcae-fd1b-4fd7-9f04-015095e81e53",
    "UserAgent": "Mozilla/5.0 (Windows NT; Windows NT 6.1; en-US) WindowsPowerShell/4.0",
    "Version": "0.0.0.0",
}
]
}